I-Type/BarrelShifter.vhd
library ieee;
use ieee.std_logic_1164.all;
use ieee.numeric_std.all;

entity BarrelShifter is
        port(
        DataIn : in std_logic_vector(31 downto 0);
        Shamt : in std_logic_vector(4 downto 0); -- số bit dịch
        Mode : in std_logic_vector(1 downto 0); -- 00=SLL, 01=SRL, 10=SRA
        DataOut : out std_logic_vector(31 downto 0)
        );
    end entity;

architecture Behavioral of BarrelShifter is

    signal stage0, stage1, stage2, stage3, stage4 : std_logic_vector(31 downto 0);
    signal fillbit : std_logic;

begin

    ------------------------------------------------------------
    -- bit điền khi dịch phải
    ------------------------------------------------------------
    fillbit <= '0' when Mode = "01" else     -- SRL
            DataIn(31) when Mode = "10" else  -- SRA
            '0';

    ------------------------------------------------------------
    -- Stage 0: dịch 1 bit
    ------------------------------------------------------------
    stage0 <= 
        DataIn(30 downto 0) & '0' when (Mode="00" and Shamt(0)='1') else  -- SLL
        fillbit & DataIn(31 downto 1) when (Shamt(0)='1') else
        DataIn;

    -- Stage 1: dịch 2 bit
    stage1 <=
        stage0(29 downto 0) & (1 downto 0 => '0') when (Mode="00" and Shamt(1)='1') else
        ( (1 downto 0 => fillbit) & stage0(31 downto 2) ) when (Shamt(1)='1') else
        stage0;

    -- Stage 2: dịch 4 bit
    stage2 <=
        stage1(27 downto 0) & (3 downto 0 => '0') when (Mode="00" and Shamt(2)='1') else
        ( (3 downto 0 => fillbit) & stage1(31 downto 4) ) when (Shamt(2)='1') else
        stage1;

    -- Stage 3: dịch 8 bit
    stage3 <=
        stage2(23 downto 0) & (7 downto 0 => '0') when (Mode="00" and Shamt(3)='1') else
        ( (7 downto 0 => fillbit) & stage2(31 downto 8) ) when (Shamt(3)='1') else
        stage2;

    -- Stage 4: dịch 16 bit
    stage4 <=
        stage3(15 downto 0) & (15 downto 0 => '0') when (Mode="00" and Shamt(4)='1') else
        ( (15 downto 0 => fillbit) & stage3(31 downto 16) ) when (Shamt(4)='1') else
        stage3;


    ------------------------------------------------------------
    -- Output
    ------------------------------------------------------------
    DataOut <= stage4;

end architecture;

BrentKung_16.vhd
-- Huy
-- Cấu trúc Brent–Kung 16-bit
-- Cây gồm 4 tầng reduce + 3 tầng distribute, tổng 7 tầng logic
-- Stage 1: Pairwise combine   (G1,G0), (G3,G2), (G5,G4), (G7,G6), (G9,G8), (G11,G10), (G13,G12), (G15,G14)
-- Stage 2: Combine every 4 bits
-- Stage 3: Combine every 8 bits
-- Stage 4: Combine every 16 bits
LIBRARY IEEE;
USE IEEE.STD_LOGIC_1164.ALL;

ENTITY BrentKung_16 IS
    PORT (
        A, B  : IN  STD_LOGIC_VECTOR(15 DOWNTO 0);
        Cin   : IN  STD_LOGIC;
        Sum   : OUT STD_LOGIC_VECTOR(15 DOWNTO 0);
        Cout  : OUT STD_LOGIC
    );
END BrentKung_16;

ARCHITECTURE PrefixTree OF BrentKung_16 IS

    TYPE GPArray IS ARRAY (15 DOWNTO 0) OF STD_LOGIC_VECTOR(1 DOWNTO 0);
    SIGNAL GP : GPArray;         -- G_i, P_i for each bit
    SIGNAL C  : STD_LOGIC_VECTOR(16 DOWNTO 0);  -- Carry signals

    -- Hàm gộp (prefix)
    FUNCTION Combine(X, Y : STD_LOGIC_VECTOR(1 DOWNTO 0)) RETURN STD_LOGIC_VECTOR IS
        VARIABLE R : STD_LOGIC_VECTOR(1 DOWNTO 0);
    BEGIN
        R(1) := X(1) AND Y(1);                 -- P_out = P_i * P_j
        R(0) := X(0) OR (X(1) AND Y(0));       -- G_out = G_i + P_i * G_j
        RETURN R;
    END FUNCTION;

    SIGNAL G, P : STD_LOGIC_VECTOR(15 DOWNTO 0);

BEGIN
    -- Tính G và P cơ bản
    GEN_GP: FOR i IN 0 TO 15 GENERATE
        G(i) <= A(i) AND B(i);
        P(i) <= A(i) XOR B(i);
    END GENERATE;

    -- Carry vào đầu tiên
    C(0) <= Cin;

    ------------------------------------------------------------------------------
    -- Reduction tree (prefix gộp)
    ------------------------------------------------------------------------------

    -- Level 1 (distance 1)
    SIGNAL G1, P1 : STD_LOGIC_VECTOR(15 DOWNTO 0);
    GEN_L1: FOR i IN 0 TO 15 GENERATE
        IF i MOD 2 = 1 THEN
            G1(i) <= G(i) OR (P(i) AND G(i-1));
            P1(i) <= P(i) AND P(i-1);
        ELSE
            G1(i) <= G(i);
            P1(i) <= P(i);
        END IF;
    END GENERATE;

    -- Level 2 (distance 2)
    SIGNAL G2, P2 : STD_LOGIC_VECTOR(15 DOWNTO 0);
    GEN_L2: FOR i IN 0 TO 15 GENERATE
        IF i MOD 4 >= 2 THEN
            G2(i) <= G1(i) OR (P1(i) AND G1(i-2));
            P2(i) <= P1(i) AND P1(i-2);
        ELSE
            G2(i) <= G1(i);
            P2(i) <= P1(i);
        END IF;
    END GENERATE;

    -- Level 3 (distance 4)
    SIGNAL G3, P3 : STD_LOGIC_VECTOR(15 DOWNTO 0);
    GEN_L3: FOR i IN 0 TO 15 GENERATE
        IF i MOD 8 >= 4 THEN
            G3(i) <= G2(i) OR (P2(i) AND G2(i-4));
            P3(i) <= P2(i) AND P2(i-4);
        ELSE
            G3(i) <= G2(i);
            P3(i) <= P2(i);
        END IF;
    END GENERATE;

    -- Level 4 (distance 8)
    SIGNAL G4, P4 : STD_LOGIC_VECTOR(15 DOWNTO 0);
    GEN_L4: FOR i IN 0 TO 15 GENERATE
        IF i >= 8 THEN
            G4(i) <= G3(i) OR (P3(i) AND G3(i-8));
            P4(i) <= P3(i) AND P3(i-8);
        ELSE
            G4(i) <= G3(i);
            P4(i) <= P3(i);
        END IF;
    END GENERATE;

    ------------------------------------------------------------------------------
    -- Distribution phase: truyền carry xuống
    ------------------------------------------------------------------------------
    C(1)  <= G(0) OR (P(0) AND C(0));
    C(2)  <= G1(1) OR (P1(1) AND C(0));
    C(3)  <= G2(2) OR (P2(2) AND C(0));
    C(4)  <= G2(3) OR (P2(3) AND C(0));
    C(5)  <= G3(4) OR (P3(4) AND C(0));
    C(6)  <= G3(5) OR (P3(5) AND C(0));
    C(7)  <= G3(6) OR (P3(6) AND C(0));
    C(8)  <= G4(7) OR (P4(7) AND C(0));
    C(9)  <= G4(8) OR (P4(8) AND C(0));
    C(10) <= G4(9) OR (P4(9) AND C(0));
    C(11) <= G4(10) OR (P4(10) AND C(0));
    C(12) <= G4(11) OR (P4(11) AND C(0));
    C(13) <= G4(12) OR (P4(12) AND C(0));
    C(14) <= G4(13) OR (P4(13) AND C(0));
    C(15) <= G4(14) OR (P4(14) AND C(0));
    C(16) <= G4(15) OR (P4(15) AND C(0));

    ------------------------------------------------------------------------------
    -- Kết quả tổng
    ------------------------------------------------------------------------------
    GEN_SUM: FOR i IN 0 TO 15 GENERATE
        Sum(i) <= P(i) XOR C(i);
    END GENERATE;

    Cout <= C(16);

END PrefixTree;

R-Type/BrentKung_32.vhd
library IEEE;
use IEEE.STD_LOGIC_1164.ALL;
use IEEE.NUMERIC_STD.ALL;

entity BrentKung_32 is
    port(
        A    : in  std_logic_vector(31 downto 0);
        B    : in  std_logic_vector(31 downto 0);
        Cin  : in  std_logic;
        Sum  : out std_logic_vector(31 downto 0);
        Cout : out std_logic
    );
end entity;

architecture Structural of BrentKung_32 is

    component BrentKung_16
        port(
            A    : in  std_logic_vector(15 downto 0);
            B    : in  std_logic_vector(15 downto 0);
            Cin  : in  std_logic;
            Sum  : out std_logic_vector(15 downto 0);
            Cout : out std_logic
        );
    end component;

    signal Sum_lo, Sum_hi : std_logic_vector(15 downto 0);
    signal Cmid            : std_logic;

begin

    BK_LOW: BrentKung_16
        port map (
            A    => A(15 downto 0),
            B    => B(15 downto 0),
            Cin  => Cin,
            Sum  => Sum_lo,
            Cout => Cmid
        );

    BK_HIGH: BrentKung_16
        port map (
            A    => A(31 downto 16),
            B    => B(31 downto 16),
            Cin  => Cmid,
            Sum  => Sum_hi,
            Cout => Cout
        );

    -- **Đúng thứ tự**: high half trước, low half sau
    Sum <= Sum_hi & Sum_lo;

end architecture;

ALU/ALU.vhd
-- Biên dịch 
-- ghdl -a BarrelShifter.vhd BrentKung_16.vhd BrentKung_32.vhd
-- ghdl -a ALU.vhd
-- ghdl -a ALU_tb.vhd

-- Xây Test_Bench + chạy mô phỏng
-- ghdl -e ALU_tb
-- ghdl -r ALU_tb --vcd=alu.vcd
-- gtkwave alu.vcd
---------------------------------------------------------------------------------------
-- Các phép toán số học 32-bit: add, sub, slt
-- Các phép toán logic 32-bit: and, or, (xor), nor
-- Các phép dịch 32-bit: sll (dịch trái), srl (dịch phải), sra (dịch số học)
-- Các phép toán cho Branch: beq, bne
---------------------------------------------------------------------------------------
-- Bảng mã ALUControl 
-- 0000	AND	A AND B
-- 0001	OR	A OR B
-- 0010	ADD	A + B
-- 0110	SUB	A – B
-- 0111	SLT	1 nếu A < B
-- 1100	NOR	NOT(A OR B)
--------------------------------------------------------------------------------------
library IEEE;
use IEEE.STD_LOGIC_1164.ALL;
use IEEE.NUMERIC_STD.ALL;

entity ALU is
    port(
        A          : in  STD_LOGIC_VECTOR(31 downto 0);
        B          : in  STD_LOGIC_VECTOR(31 downto 0);
        ALUControl : in  STD_LOGIC_VECTOR(3 downto 0);
        Result     : out STD_LOGIC_VECTOR(31 downto 0);
        Zero       : out STD_LOGIC
    );
end entity;

architecture Behavioral of ALU is

    -- Component bộ cộng 32 bit Brent-Kung
    component BrentKung_32
        port(
            A, B : in  STD_LOGIC_VECTOR(31 downto 0);
            Cin  : in  STD_LOGIC;
            Sum  : out STD_LOGIC_VECTOR(31 downto 0);
            Cout : out STD_LOGIC
        );
    end component;
    -- Component bộ dịch BarrelShifter 32 bit
    component BarrelShifter
        port(
            DataIn  : in  std_logic_vector(31 downto 0);
            Shamt   : in  std_logic_vector(4 downto 0); -- số bit dịch
            Mode    : in  std_logic_vector(1 downto 0); -- 00=SLL, 01=SRL, 10=SRA
            DataOut : out std_logic_vector(31 downto 0)
        );
    end component;
    

    signal B_invert     : STD_LOGIC_VECTOR(31 downto 0); 
    signal adder_result : STD_LOGIC_VECTOR(31 downto 0);
    signal Cin_sig      : STD_LOGIC := '0';
    signal Result_i : STD_LOGIC_VECTOR(31 downto 0);
    signal shiftOut : STD_LOGIC_VECTOR(31 downto 0);
begin

    -----------------------------------------------------------
    -- Chọn B hoặc NOT B và xác định Cin
    -----------------------------------------------------------
    process(A, B, ALUControl)
    begin
        case ALUControl is
        
            when "0010" =>  -- ADD
                B_invert <= B;
                Cin_sig  <= '0';

            when "0110" =>  -- SUB
                B_invert <= NOT B;
                Cin_sig  <= '1';  -- để thực hiện A + (~B) + 1

            when "0111" =>  -- SLT (dùng phép trừ phía trong)
                B_invert <= NOT B;
                Cin_sig  <= '1';

            when others =>
                B_invert <= B;
                Cin_sig  <= '0';
        end case;
    end process;


    -----------------------------------------------------------
    -- Gọi bộ cộng Brent-Kung 32 bit
    -----------------------------------------------------------
    Adder32: BrentKung_32
        port map(
            A    => A,
            B    => B_invert,
            Cin  => Cin_sig,
            Sum  => adder_result,
            Cout => open
        );
    -----------------------------------------------------------
    -- Gọi bộ dịch BarrelShifter 32 bit
    -----------------------------------------------------------
    U_SHIFTER : entity work.BarrelShifter
        port map(
            DataIn  => A,
            Shamt   => B(4 downto 0), -- 5 bit dịch
            Mode    => ALUControl(1 downto 0),
            DataOut => shiftOut -- kết quả dịch
        );

    -----------------------------------------------------------
    -- Cho ra kết quả ALU
    -----------------------------------------------------------
    process(A, B, ALUControl, adder_result, shiftOut)
    begin
        case ALUControl is

            when "0000" =>   -- AND
                Result_i <= A AND B;

            when "0001" =>   -- OR
                Result_i <= A OR B;

            when "0010" =>   -- ADD
                Result_i <= adder_result;

            when "0110" =>   -- SUB
                Result_i <= adder_result;

            when "0111" =>   -- SLT
                if adder_result(31) = '1' then
                    Result_i <= (others => '0');
                    Result_i(0) <= '1';
                else
                    Result_i <= (others => '0');
                end if;

            when "1100" =>  -- NOR
                Result_i <= NOT (A OR B);
                
            when "0100" =>  -- XOR
                Result_i <= A XOR B;

            when "1000"  =>  -- SLL
                Result_i <= shiftOut;
            when "1001"  =>  -- SRL
                Result_i <= shiftOut;
            when "1010" =>  -- SRA
                Result_i <= shiftOut;

            when others =>
                Result_i <= (others => '0');
        end case;
    end process;


    -----------------------------------------------------------
    -- Xuất kết quả ra port
    -----------------------------------------------------------
    Result <= Result_i;


    -----------------------------------------------------------
    -- Zero flag
    -----------------------------------------------------------
    Zero <= '1' when Result_i = x"00000000" else '0';

end architecture;

ALU/ALU_tb.vhd
-- ghdl -a BrentKung_16.vhd BrentKung_32.vhd BarrelShifter.vhd ALU.vhd ALU_tb.vhd
-- ghdl -e ALU_tb
-- ghdl -r ALU_tb --vcd=alu.vcd
-- gtkwave alu.vcd

library ieee;
use ieee.std_logic_1164.all;
use ieee.numeric_std.all;

entity ALU_tb is
end entity;

architecture sim of ALU_tb is

    -- Component ALU
    component ALU
        port(
            A          : in  STD_LOGIC_VECTOR(31 downto 0);
            B          : in  STD_LOGIC_VECTOR(31 downto 0);
            ALUControl : in  STD_LOGIC_VECTOR(3 downto 0);
            Result     : out STD_LOGIC_VECTOR(31 downto 0);
            Zero       : out STD_LOGIC
        );
    end component;

    signal A_s, B_s     : STD_LOGIC_VECTOR(31 downto 0);
    signal Control_s    : STD_LOGIC_VECTOR(3 downto 0);
    signal Result_s     : STD_LOGIC_VECTOR(31 downto 0);
    signal Zero_s       : STD_LOGIC;

    constant delay_t : time := 20 ns;

begin

    -- Kết nối DUT
    DUT : ALU
        port map(
            A          => A_s,
            B          => B_s,
            ALUControl => Control_s,
            Result     => Result_s,
            Zero       => Zero_s
        );

    -----------------------------------------------------------
    -- Vùng kiểm tra mô phỏng
    -----------------------------------------------------------
    process
    begin

        ----------------------------------------------------------------
        report "=== Test 1: ADD ===";
        ----------------------------------------------------------------
        A_s <= x"00000005";      -- 5
        B_s <= x"00000008";      -- 8
        Control_s <= "0010";     -- ADD
        wait for delay_t;

        ----------------------------------------------------------------
        report "=== Test 2: SUB ===";
        ----------------------------------------------------------------
        A_s <= x"0000000C";      -- 12
        B_s <= x"00000005";      -- 5
        Control_s <= "0110";     -- SUB
        wait for delay_t;

        ----------------------------------------------------------------
        report "=== Test 3: AND ===";
        ----------------------------------------------------------------
        A_s <= x"00000005";      -- 0101
        B_s <= x"00000008";      -- 1000
        Control_s <= "0000";     -- AND
        wait for delay_t;

        ----------------------------------------------------------------
        report "=== Test 4: OR ===";
        ----------------------------------------------------------------
        Control_s <= "0001";     -- OR
        wait for delay_t;

        ----------------------------------------------------------------
        report "=== Test 5: XOR ===";
        ----------------------------------------------------------------
        Control_s <= "0100";     -- XOR
        wait for delay_t;

        ----------------------------------------------------------------
        report "=== Test 6: NOR ===";
        ----------------------------------------------------------------
        Control_s <= "1100";     -- NOR
        wait for delay_t;

        ----------------------------------------------------------------
        report "=== Test 7: SLT (A < B) ===";
        ----------------------------------------------------------------
        A_s <= x"00000005";
        B_s <= x"00000008";
        Control_s <= "0111";     -- SLT
        wait for delay_t;

        ----------------------------------------------------------------
        report "=== Test 8: SLL (5 << 2 = 20) ===";
        ----------------------------------------------------------------
        A_s <= x"00000005";      -- value
        B_s <= x"00000002";      -- shift amount
        Control_s <= "1000";     -- SLL
        wait for delay_t;

        ----------------------------------------------------------------
        report "=== Test 9: SRL (12 >> 1 = 6) ===";
        ----------------------------------------------------------------
        A_s <= x"0000000C";      
        B_s <= x"00000001";
        Control_s <= "1001";     -- SRL
        wait for delay_t;

        ----------------------------------------------------------------
        report "=== Test 10: SRA (signed shift) ===";
        ----------------------------------------------------------------
        A_s <= x"FFFFFFF0";      -- -16
        B_s <= x"00000002";      -- >> 2
        Control_s <= "1010";     -- SRA
        wait for delay_t;

        ----------------------------------------------------------------
        report "*** TEST DONE ***";
        ----------------------------------------------------------------
        wait;
    end process;

end architecture;

ALU/alu.vcd
$date
  Mon Nov 24 09:20:13 2025
$end
$version
  GHDL v0
$end
$timescale
  1 fs
$end
$scope module standard $end
$upscope $end
$scope module std_logic_1164 $end
$upscope $end
$scope module numeric_std $end
$upscope $end
$scope module alu_tb $end
$var reg 32 ! a_s[31:0] $end
$var reg 32 " b_s[31:0] $end
$var reg 4 # control_s[3:0] $end
$var reg 32 $ result_s[31:0] $end
$var reg 1 % zero_s $end
$scope module dut $end
$var reg 32 & a[31:0] $end
$var reg 32 ' b[31:0] $end
$var reg 4 ( alucontrol[3:0] $end
$var reg 32 ) result[31:0] $end
$var reg 1 * zero $end
$var reg 32 + b_invert[31:0] $end
$var reg 32 , adder_result[31:0] $end
$var reg 1 - cin_sig $end
$var reg 32 . result_i[31:0] $end
$var reg 32 / shiftout[31:0] $end
$scope module adder32 $end
$var reg 32 0 a[31:0] $end
$var reg 32 1 b[31:0] $end
$var reg 1 2 cin $end
$var reg 32 3 sum[31:0] $end
$var reg 1 4 cout $end
$var reg 16 5 sum_lo[15:0] $end
$var reg 16 6 sum_hi[15:0] $end
$var reg 1 7 cmid $end
$scope module bk_low $end
$var reg 16 8 a[15:0] $end
$var reg 16 9 b[15:0] $end
$var reg 1 : cin $end
$var reg 16 ; sum[15:0] $end
$var reg 1 < cout $end
$var reg 16 = g[15:0] $end
$var reg 16 > p[15:0] $end
$var reg 17 ? c[16:0] $end
$scope module gen_gp(0) $end
$upscope $end
$scope module gen_gp(1) $end
$upscope $end
$scope module gen_gp(2) $end
$upscope $end
$scope module gen_gp(3) $end
$upscope $end
$scope module gen_gp(4) $end
$upscope $end
$scope module gen_gp(5) $end
$upscope $end
$scope module gen_gp(6) $end
$upscope $end
$scope module gen_gp(7) $end
$upscope $end
$scope module gen_gp(8) $end
$upscope $end
$scope module gen_gp(9) $end
$upscope $end
$scope module gen_gp(10) $end
$upscope $end
$scope module gen_gp(11) $end
$upscope $end
$scope module gen_gp(12) $end
$upscope $end
$scope module gen_gp(13) $end
$upscope $end
$scope module gen_gp(14) $end
$upscope $end
$scope module gen_gp(15) $end
$upscope $end
$scope module gen_sum(0) $end
$upscope $end
$scope module gen_sum(1) $end
$upscope $end
$scope module gen_sum(2) $end
$upscope $end
$scope module gen_sum(3) $end
$upscope $end
$scope module gen_sum(4) $end
$upscope $end
$scope module gen_sum(5) $end
$upscope $end
$scope module gen_sum(6) $end
$upscope $end
$scope module gen_sum(7) $end
$upscope $end
$scope module gen_sum(8) $end
$upscope $end
$scope module gen_sum(9) $end
$upscope $end
$scope module gen_sum(10) $end
$upscope $end
$scope module gen_sum(11) $end
$upscope $end
$scope module gen_sum(12) $end
$upscope $end
$scope module gen_sum(13) $end
$upscope $end
$scope module gen_sum(14) $end
$upscope $end
$scope module gen_sum(15) $end
$upscope $end
$upscope $end
$scope module bk_high $end
$var reg 16 @ a[15:0] $end
$var reg 16 A b[15:0] $end
$var reg 1 B cin $end
$var reg 16 C sum[15:0] $end
$var reg 1 D cout $end
$var reg 16 E g[15:0] $end
$var reg 16 F p[15:0] $end
$var reg 17 G c[16:0] $end
$scope module gen_gp(0) $end
$upscope $end
$scope module gen_gp(1) $end
$upscope $end
$scope module gen_gp(2) $end
$upscope $end
$scope module gen_gp(3) $end
$upscope $end
$scope module gen_gp(4) $end
$upscope $end
$scope module gen_gp(5) $end
$upscope $end
$scope module gen_gp(6) $end
$upscope $end
$scope module gen_gp(7) $end
$upscope $end
$scope module gen_gp(8) $end
$upscope $end
$scope module gen_gp(9) $end
$upscope $end
$scope module gen_gp(10) $end
$upscope $end
$scope module gen_gp(11) $end
$upscope $end
$scope module gen_gp(12) $end
$upscope $end
$scope module gen_gp(13) $end
$upscope $end
$scope module gen_gp(14) $end
$upscope $end
$scope module gen_gp(15) $end
$upscope $end
$scope module gen_sum(0) $end
$upscope $end
$scope module gen_sum(1) $end
$upscope $end
$scope module gen_sum(2) $end
$upscope $end
$scope module gen_sum(3) $end
$upscope $end
$scope module gen_sum(4) $end
$upscope $end
$scope module gen_sum(5) $end
$upscope $end
$scope module gen_sum(6) $end
$upscope $end
$scope module gen_sum(7) $end
$upscope $end
$scope module gen_sum(8) $end
$upscope $end
$scope module gen_sum(9) $end
$upscope $end
$scope module gen_sum(10) $end
$upscope $end
$scope module gen_sum(11) $end
$upscope $end
$scope module gen_sum(12) $end
$upscope $end
$scope module gen_sum(13) $end
$upscope $end
$scope module gen_sum(14) $end
$upscope $end
$scope module gen_sum(15) $end
$upscope $end
$upscope $end
$upscope $end
$scope module u_shifter $end
$var reg 32 H datain[31:0] $end
$var reg 5 I shamt[4:0] $end
$var reg 2 J mode[1:0] $end
$var reg 32 K dataout[31:0] $end
$var reg 32 L stage0[31:0] $end
$var reg 32 M stage1[31:0] $end
$var reg 32 N stage2[31:0] $end
$var reg 32 O stage3[31:0] $end
$var reg 32 P stage4[31:0] $end
$var reg 1 Q fillbit $end
$upscope $end
$upscope $end
$upscope $end
$enddefinitions $end
#0
b00000000000000000000000000000101 !
b00000000000000000000000000001000 "
b0010 #
b00000000000000000000000000001101 $
0%
b00000000000000000000000000000101 &
b00000000000000000000000000001000 '
b0010 (
b00000000000000000000000000001101 )
0*
b00000000000000000000000000001000 +
b00000000000000000000000000001101 ,
0-
b00000000000000000000000000001101 .
b00000000000000000000000000000000 /
b00000000000000000000000000000101 0
b00000000000000000000000000001000 1
02
b00000000000000000000000000001101 3
04
b0000000000001101 5
b0000000000000000 6
07
b0000000000000101 8
b0000000000001000 9
0:
b0000000000001101 ;
0<
b0000000000000000 =
b0000000000001101 >
b00000000000000000 ?
b0000000000000000 @
b0000000000000000 A
0B
b0000000000000000 C
0D
b0000000000000000 E
b0000000000000000 F
b00000000000000000 G
b00000000000000000000000000000101 H
b01000 I
b10 J
b00000000000000000000000000000000 K
b00000000000000000000000000000101 L
b00000000000000000000000000000101 M
b00000000000000000000000000000101 N
b00000000000000000000000000000000 O
b00000000000000000000000000000000 P
0Q
#20000000
b00000000000000000000000000001100 !
b00000000000000000000000000000101 "
b0110 #
b00000000000000000000000000000111 $
b00000000000000000000000000001100 &
b00000000000000000000000000000101 '
b0110 (
b00000000000000000000000000000111 )
b11111111111111111111111111111010 +
b00000000000000000000000000000111 ,
1-
b00000000000000000000000000000111 .
b00000000000000000000000000000000 /
b00000000000000000000000000001100 0
b11111111111111111111111111111010 1
12
b00000000000000000000000000000111 3
14
b0000000000000111 5
b0000000000000000 6
17
b0000000000001100 8
b1111111111111010 9
1:
b0000000000000111 ;
1<
b0000000000001000 =
b1111111111110110 >
b11111111111110001 ?
b1111111111111111 A
1B
b0000000000000000 C
1D
b1111111111111111 F
b11111111111111111 G
b00000000000000000000000000001100 H
b00101 I
b00000000000000000000000000000000 K
b00000000000000000000000000000110 L
b00000000000000000000000000000110 M
b00000000000000000000000000000000 N
b00000000000000000000000000000000 O
b00000000000000000000000000000000 P
#40000000
b00000000000000000000000000000101 !
b00000000000000000000000000001000 "
b0000 #
b00000000000000000000000000000000 $
1%
b00000000000000000000000000000101 &
b00000000000000000000000000001000 '
b0000 (
b00000000000000000000000000000000 )
1*
b00000000000000000000000000001000 +
b00000000000000000000000000001101 ,
0-
b00000000000000000000000000000000 .
b00000000000000000000010100000000 /
b00000000000000000000000000000101 0
b00000000000000000000000000001000 1
02
b00000000000000000000000000001101 3
04
b0000000000001101 5
b0000000000000000 6
07
b0000000000000101 8
b0000000000001000 9
0:
b0000000000001101 ;
0<
b0000000000000000 =
b0000000000001101 >
b00000000000000000 ?
b0000000000000000 A
0B
b0000000000000000 C
0D
b0000000000000000 F
b00000000000000000 G
b00000000000000000000000000000101 H
b01000 I
b00 J
b00000000000000000000010100000000 K
b00000000000000000000000000000101 L
b00000000000000000000000000000101 M
b00000000000000000000000000000101 N
b00000000000000000000010100000000 O
b00000000000000000000010100000000 P
#60000000
b0001 #
b00000000000000000000000000001101 $
0%
b0001 (
b00000000000000000000000000001101 )
0*
b00000000000000000000000000001101 .
b00000000000000000000000000000000 /
b01 J
b00000000000000000000000000000000 K
b00000000000000000000000000000000 O
b00000000000000000000000000000000 P
#80000000
b0100 #
b0100 (
b00000000000000000000010100000000 /
b00 J
b00000000000000000000010100000000 K
b00000000000000000000010100000000 O
b00000000000000000000010100000000 P
#100000000
b1100 #
b11111111111111111111111111110010 $
b1100 (
b11111111111111111111111111110010 )
b11111111111111111111111111110010 .
#120000000
b0111 #
b00000000000000000000000000000001 $
0%
b0111 (
b00000000000000000000000000000001 )
0*
b11111111111111111111111111110111 +
b11111111111111111111111111111101 ,
1-
b00000000000000000000000000000001 .
b00000000000000000000000000000000 /
b11111111111111111111111111110111 1
12
b11111111111111111111111111111101 3
b1111111111111101 5
b1111111111111111 6
b1111111111110111 9
1:
b1111111111111101 ;
b0000000000000101 =
b1111111111110010 >
b00000000000001111 ?
b1111111111111111 A
b1111111111111111 C
b1111111111111111 F
b11 J
b00000000000000000000000000000000 K
b00000000000000000000000000000000 O
b00000000000000000000000000000000 P
#140000000
b00000000000000000000000000000010 "
b1000 #
b00000000000000000000000000010100 $
0%
b00000000000000000000000000000010 '
b1000 (
b00000000000000000000000000010100 )
0*
b00000000000000000000000000000010 +
b00000000000000000000000000000111 ,
0-
b00000000000000000000000000010100 .
b00000000000000000000000000010100 /
b00000000000000000000000000000010 1
02
b00000000000000000000000000000111 3
b0000000000000111 5
b0000000000000000 6
b0000000000000010 9
0:
b0000000000000111 ;
b0000000000000000 =
b0000000000000111 >
b00000000000000000 ?
b0000000000000000 A
b0000000000000000 C
b0000000000000000 F
b00010 I
b00 J
b00000000000000000000000000010100 K
b00000000000000000000000000010100 M
b00000000000000000000000000010100 N
b00000000000000000000000000010100 O
b00000000000000000000000000010100 P
#160000000
b00000000000000000000000000001100 !
b00000000000000000000000000000001 "
b1001 #
b00000000000000000000000000001100 &
b00000000000000000000000000000001 '
b1001 (
b00000000000000000000000000000001 +
b00000000000000000000000000001101 ,
b00000000000000000000000000000110 /
b00000000000000000000000000001100 0
b00000000000000000000000000000001 1
b00000000000000000000000000001101 3
b0000000000001101 5
b0000000000001100 8
b0000000000000001 9
b0000000000001101 ;
b0000000000001101 >
b00000000000000000000000000001100 H
b00001 I
b01 J
b00000000000000000000000000000110 K
b00000000000000000000000000000110 L
b00000000000000000000000000000110 M
b00000000000000000000000000000110 N
b00000000000000000000000000000110 O
b00000000000000000000000000000110 P
#180000000
b11111111111111111111111111110000 !
b00000000000000000000000000000010 "
b1010 #
b00000000000000000000000000000110 $
b11111111111111111111111111110000 &
b00000000000000000000000000000010 '
b1010 (
b00000000000000000000000000000110 )
b00000000000000000000000000000010 +
b11111111111111111111111111110010 ,
b00000000000000000000000000000110 .
b11111111111111111111111111111100 /
b11111111111111111111111111110000 0
b00000000000000000000000000000010 1
b11111111111111111111111111110010 3
b1111111111110010 5
b1111111111111111 6
b1111111111110000 8
b0000000000000010 9
b1111111111110010 ;
b1111111111110010 >
b1111111111111111 @
b1111111111111111 C
b1111111111111111 F
b11111111111111111111111111110000 H
b00010 I
b10 J
b11111111111111111111111111111100 K
b11111111111111111111111111110000 L
b11111111111111111111111111111100 M
b11111111111111111111111111111100 N
b11111111111111111111111111111100 O
b11111111111111111111111111111100 P
1Q
